str_maker/__init__.py
str_maker/test.py
str_maker-0.0.dist-info/METADATA
str_maker-0.0.dist-info/WHEEL
str_maker-0.0.dist-info/top_level.txt
str_maker-0.0.dist-info/RECORD
