Metadata-Version: 2.1
Name: str-maker
Version: 0.0
Summary: it's for testing
Home-page: UNKNOWN
Author: AAAAA
Author-email: ypil@molpax.com
License: MIT
Platform: UNKNOWN
Classifier: Programming Language :: Python :: 3
Classifier: License :: OSI Approved :: MIT License
Classifier: Operating System :: OS Independent
